hydrotopo/__init__.py
hydrotopo/cli.py
hydrotopo/ig_path.py
hydrotopo/ig_path_test.py
hydrotopo-0.1.2.dist-info/licenses/LICENSE
hydrotopo-0.1.2.dist-info/METADATA
hydrotopo-0.1.2.dist-info/WHEEL
hydrotopo-0.1.2.dist-info/entry_points.txt
hydrotopo-0.1.2.dist-info/top_level.txt
hydrotopo-0.1.2.dist-info/RECORD
