Metadata-Version: 2.4
Name: hydrotopo
Version: 0.1.2
Summary: A project which find topologic relations among stations along rivers
Home-page: https://github.com/iHeadWater/HydroTopo
Author: forestbat
License: MIT
Keywords: hydrotopo
Classifier: Development Status :: 2 - Pre-Alpha
Classifier: Intended Audience :: Developers
Classifier: License :: OSI Approved :: MIT License
Classifier: Natural Language :: English
Classifier: Programming Language :: Python :: 3.9
Classifier: Programming Language :: Python :: 3.10
Classifier: Programming Language :: Python :: 3.11
Classifier: Programming Language :: Python :: 3.12
Classifier: Programming Language :: Python :: Implementation :: CPython
Classifier: Programming Language :: Python :: Implementation :: PyPy
License-File: LICENSE
Requires-Dist: geopandas>=0.12.2
Requires-Dist: pytest>=7.1.3
Requires-Dist: setuptools>=70.0.0
Requires-Dist: click>=8.1.3
Requires-Dist: pandas>=1.4.3
Requires-Dist: shapely>=2.0.1
Requires-Dist: pyogrio>=0.4.2
Requires-Dist: igraph>=0.10.4
Dynamic: author
Dynamic: classifier
Dynamic: description
Dynamic: home-page
Dynamic: keywords
Dynamic: license
Dynamic: license-file
Dynamic: requires-dist
Dynamic: summary
